cryt/__init__.py
cryt/base.py
cryt/client.py
cryt/client_async.py
cryt_python-0.0.4.dist-info/WHEEL
cryt_python-0.0.4.dist-info/METADATA
cryt_python-0.0.4.dist-info/RECORD
