Metadata-Version: 2.1
Name: cryt-python
Version: 0.0.4
Summary: 
Author: Aleksander Skiridomov
Author-email: aleksander.skiridomov@cryt.com
Requires-Python: >=3.11,<4.0
Classifier: Programming Language :: Python :: 3
Classifier: Programming Language :: Python :: 3.11
Requires-Dist: aiohttp (>=3.8.3,<4.0.0)
Requires-Dist: requests (>=2.28.1,<3.0.0)
